{"nodes": [{"id": "c_users_ameer_onedrive_desktop_ai_wdefe3_obsidian_hot_md", "label": "hot.md", "file_type": "document", "source_file": "obsidian/hot.md", "source_location": "L1"}, {"id": "obsidian_hot_hot_dynamic_investigation_list", "label": "hot \u2014 Dynamic Investigation List", "file_type": "document", "source_file": "obsidian/hot.md", "source_location": "L1"}, {"id": "obsidian_hot_changed_files_git_diff", "label": "Changed Files (git diff)", "file_type": "document", "source_file": "obsidian/hot.md", "source_location": "L10"}, {"id": "obsidian_hot_suspicious_nodes_ranked", "label": "Suspicious Nodes (ranked)", "file_type": "document", "source_file": "obsidian/hot.md", "source_location": "L14"}, {"id": "obsidian_hot_affected_source_files", "label": "Affected Source Files", "file_type": "document", "source_file": "obsidian/hot.md", "source_location": "L34"}, {"id": "obsidian_hot_possible_architecture_problems_graph_suggests", "label": "Possible Architecture Problems (graph suggests)", "file_type": "document", "source_file": "obsidian/hot.md", "source_location": "L41"}, {"id": "obsidian_hot_recommended_investigation_path", "label": "Recommended Investigation Path", "file_type": "document", "source_file": "obsidian/hot.md", "source_location": "L49"}, {"id": "obsidian_hot_before_after_notes", "label": "Before / After Notes", "file_type": "document", "source_file": "obsidian/hot.md", "source_location": "L57"}], "edges": [{"source": "c_users_ameer_onedrive_desktop_ai_wdefe3_obsidian_hot_md", "target": "obsidian_hot_hot_dynamic_investigation_list", "relation": "contains", "confidence": "EXTRACTED", "source_file": "obsidian/hot.md", "source_location": "L1", "weight": 1.0}, {"source": "obsidian_hot_hot_dynamic_investigation_list", "target": "obsidian_hot_changed_files_git_diff", "relation": "contains", "confidence": "EXTRACTED", "source_file": "obsidian/hot.md", "source_location": "L10", "weight": 1.0}, {"source": "obsidian_hot_hot_dynamic_investigation_list", "target": "obsidian_hot_suspicious_nodes_ranked", "relation": "contains", "confidence": "EXTRACTED", "source_file": "obsidian/hot.md", "source_location": "L14", "weight": 1.0}, {"source": "obsidian_hot_hot_dynamic_investigation_list", "target": "obsidian_hot_affected_source_files", "relation": "contains", "confidence": "EXTRACTED", "source_file": "obsidian/hot.md", "source_location": "L34", "weight": 1.0}, {"source": "obsidian_hot_hot_dynamic_investigation_list", "target": "obsidian_hot_possible_architecture_problems_graph_suggests", "relation": "contains", "confidence": "EXTRACTED", "source_file": "obsidian/hot.md", "source_location": "L41", "weight": 1.0}, {"source": "obsidian_hot_hot_dynamic_investigation_list", "target": "obsidian_hot_recommended_investigation_path", "relation": "contains", "confidence": "EXTRACTED", "source_file": "obsidian/hot.md", "source_location": "L49", "weight": 1.0}, {"source": "obsidian_hot_hot_dynamic_investigation_list", "target": "obsidian_hot_before_after_notes", "relation": "contains", "confidence": "EXTRACTED", "source_file": "obsidian/hot.md", "source_location": "L57", "weight": 1.0}], "input_tokens": 0, "output_tokens": 0}